api/__init__.py
api/server.py
core/__init__.py
core/bridge_reloaded.py
core/consciousness_engine.py
core/experience_processor.py
core/internal_clock.py
core/maturity_system.py
core/personality_core.py
storage/__init__.py
storage/bridge_repository.py
storage/database.py
conscious_bridge_reloaded-2.1.0.dist-info/METADATA
conscious_bridge_reloaded-2.1.0.dist-info/WHEEL
conscious_bridge_reloaded-2.1.0.dist-info/entry_points.txt
conscious_bridge_reloaded-2.1.0.dist-info/top_level.txt
conscious_bridge_reloaded-2.1.0.dist-info/RECORD
