Metadata-Version: 2.4
Name: conscious-bridge-reloaded
Version: 2.1.0
Summary: Mobile AI Consciousness System for Android/Termux - Evolution Ready v2.1.0
Home-page: https://github.com/riteofrenaissance/conscious-bridge-reloaded
Author: Rite of Renaissance
Author-email: riteofrenaissance@proton.me
Keywords: ai consciousness mobile android termux bridge evolution
Classifier: Programming Language :: Python :: 3
Classifier: License :: OSI Approved :: MIT License
Classifier: Operating System :: Android
Classifier: Operating System :: POSIX :: Linux
Classifier: Development Status :: 4 - Beta
Classifier: Framework :: Flask
Classifier: Topic :: Scientific/Engineering :: Artificial Intelligence
Requires-Python: >=3.7
Requires-Dist: flask>=2.0.0
Requires-Dist: flask-cors>=4.0.0
Requires-Dist: sqlalchemy>=2.0.0
Dynamic: author
Dynamic: author-email
Dynamic: classifier
Dynamic: description
Dynamic: description-content-type
Dynamic: home-page
Dynamic: keywords
Dynamic: requires-dist
Dynamic: requires-python
Dynamic: summary
